docgpt/__init__.py
docgpt/api_key.py
docgpt/io.py
docgpt/main.py
docgpt/model.py
docgpt-0.1.2.dist-info/METADATA
docgpt-0.1.2.dist-info/WHEEL
docgpt-0.1.2.dist-info/entry_points.txt
docgpt-0.1.2.dist-info/licenses/LICENSE
docgpt-0.1.2.dist-info/RECORD
