Metadata-Version: 2.1
Name: docgpt
Version: 0.1.2
Summary: Auto-generate documentation for code.
Project-URL: Homepage, https://github.com/amir-abdi/docgpt
Project-URL: Documentation, https://github.com/amir-abdi/docgpt
Project-URL: Bug Tracker, https://github.com/amir-abdi/docgpt/issues
Project-URL: Discussions, https://github.com/amir-abdi/docgpt/issues
Project-URL: Changelog, https://github.com/amir-abdi/docgpt/blob/main/CHANGELOG.md
Author: Amir Abdi
License:                     GNU GENERAL PUBLIC LICENSE
License-File: LICENSE
Classifier: License :: OSI Approved :: GNU General Public License v3 (GPLv3)
Classifier: Operating System :: OS Independent
Classifier: Programming Language :: Python :: 3
Requires-Python: >=3.6
Requires-Dist: jsonargparse[signatures]
Requires-Dist: openai<1.0,>=0.25.0
